graphslim/__init__.py
graphslim/config.py
graphslim/run_eval.py
graphslim/utils.py
graphslim/coarsening/__init__.py
graphslim/coarsening/affinity_gs.py
graphslim/coarsening/algebraic_jc.py
graphslim/coarsening/averaging.py
graphslim/coarsening/clustering.py
graphslim/coarsening/clusteringagg.py
graphslim/coarsening/coarsening_base.py
graphslim/coarsening/heavy_edge.py
graphslim/coarsening/kron.py
graphslim/coarsening/utils.py
graphslim/coarsening/variation_cliques.py
graphslim/coarsening/variation_edges.py
graphslim/coarsening/variation_neighborhoods.py
graphslim/coarsening/vng.py
graphslim/condensation/__init__.py
graphslim/condensation/doscond.py
graphslim/condensation/doscondx.py
graphslim/condensation/gcdm.py
graphslim/condensation/gcdmx.py
graphslim/condensation/gcond.py
graphslim/condensation/gcond_base.py
graphslim/condensation/gcondx.py
graphslim/condensation/gcsntk.py
graphslim/condensation/gdem.py
graphslim/condensation/gecc.py
graphslim/condensation/geom.py
graphslim/condensation/mirage.py
graphslim/condensation/msgc.py
graphslim/condensation/sfgc.py
graphslim/condensation/sgdd.py
graphslim/condensation/simgc.py
graphslim/condensation/utils.py
graphslim/configs/doscond/amazon.json
graphslim/configs/doscond/citeseer.json
graphslim/configs/doscond/cora.json
graphslim/configs/doscond/flickr.json
graphslim/configs/doscond/ogbn-arxiv.json
graphslim/configs/doscond/pubmed.json
graphslim/configs/doscond/reddit.json
graphslim/configs/doscond/yelp.json
graphslim/configs/doscondx/amazon.json
graphslim/configs/doscondx/citeseer.json
graphslim/configs/doscondx/cora.json
graphslim/configs/doscondx/flickr.json
graphslim/configs/doscondx/ogbn-arxiv.json
graphslim/configs/doscondx/pubmed.json
graphslim/configs/doscondx/reddit.json
graphslim/configs/doscondx/yelp.json
graphslim/configs/gcdm/amazon.json
graphslim/configs/gcdm/citeseer.json
graphslim/configs/gcdm/cora.json
graphslim/configs/gcdm/flickr.json
graphslim/configs/gcdm/ogbn-arxiv.json
graphslim-1.2.1.dist-info/licenses/LICENSE
graphslim-1.2.1.dist-info/METADATA
graphslim-1.2.1.dist-info/WHEEL
graphslim-1.2.1.dist-info/top_level.txt
graphslim-1.2.1.dist-info/RECORD
