Metadata-Version: 2.4
Name: graphslim
Version: 1.2.1
Summary: Slimming the graph data for graph learning
Author-email: Rockcor <jshmhsb@gmail.com>
License-Expression: MIT
Classifier: Intended Audience :: Developers
Classifier: Intended Audience :: Education
Classifier: Intended Audience :: Science/Research
Classifier: Programming Language :: Python :: 3
Classifier: Topic :: Scientific/Engineering :: Mathematics
Classifier: Topic :: Software Development :: Libraries :: Python Modules
Classifier: Topic :: Software Development :: Libraries
Requires-Python: <=3.11,>=3.9
License-File: LICENSE
Requires-Dist: click
Requires-Dist: deeprobust
Requires-Dist: gdown
Requires-Dist: networkit
Requires-Dist: networkx
Requires-Dist: numpy
Requires-Dist: ogb
Requires-Dist: PyGSP
Requires-Dist: scikit_learn
Requires-Dist: scipy
Requires-Dist: sortedcontainers
Requires-Dist: torch
Requires-Dist: torch_geometric
Requires-Dist: tqdm
Dynamic: license-file
